jobinformation/__init__.py
jobinformation/main.py
jobinformation-1.0.3.dist-info/licenses/LICENSE
jobinformation-1.0.3.dist-info/METADATA
jobinformation-1.0.3.dist-info/WHEEL
jobinformation-1.0.3.dist-info/entry_points.txt
jobinformation-1.0.3.dist-info/top_level.txt
jobinformation-1.0.3.dist-info/RECORD
